invenio_records_global_search/__init__.py
invenio_records_global_search/cli.py
invenio_records_global_search/config.py
invenio_records_global_search/ext.py
invenio_records_global_search/proxies.py
invenio_records_global_search/views.py
invenio_records_global_search/webpack.py
invenio_records_global_search/assets/semantic-ui/js/invenio_records_global_search/search/index.js
invenio_records_global_search/assets/semantic-ui/js/invenio_records_global_search/search/components/GlobalSearchBucketAggregationElement.js
invenio_records_global_search/assets/semantic-ui/js/invenio_records_global_search/search/components/GlobalSearchEmptyResults.js
invenio_records_global_search/assets/semantic-ui/js/invenio_records_global_search/search/components/GlobalSearchRecordResultsGridItem.js
invenio_records_global_search/assets/semantic-ui/js/invenio_records_global_search/search/components/GlobalSearchRecordResultsListItem.js
invenio_records_global_search/assets/semantic-ui/js/invenio_records_global_search/search/components/index.js
invenio_records_global_search/assets/semantic-ui/less/invenio_records_global_search/theme.less
invenio_records_global_search/assets/semantic-ui/less/invenio_records_global_search/variables.less
invenio_records_global_search/assets/semantic-ui/translations/invenio_records_global_search/i18next-scanner.config.js
invenio_records_global_search/assets/semantic-ui/translations/invenio_records_global_search/i18next.js
invenio_records_global_search/assets/semantic-ui/translations/invenio_records_global_search/package-lock.json
invenio_records_global_search/assets/semantic-ui/translations/invenio_records_global_search/package.json
invenio_records_global_search/assets/semantic-ui/translations/invenio_records_global_search/translations.pot
invenio_records_global_search/assets/semantic-ui/translations/invenio_records_global_search/messages/index.js
invenio_records_global_search/assets/semantic-ui/translations/invenio_records_global_search/messages/de/translations.json
invenio_records_global_search-0.3.5.dist-info/licenses/AUTHORS.rst
invenio_records_global_search-0.3.5.dist-info/licenses/LICENSE
invenio_records_global_search-0.3.5.dist-info/METADATA
invenio_records_global_search-0.3.5.dist-info/WHEEL
invenio_records_global_search-0.3.5.dist-info/entry_points.txt
invenio_records_global_search-0.3.5.dist-info/top_level.txt
invenio_records_global_search-0.3.5.dist-info/RECORD
