Metadata-Version: 2.4
Name: invenio-records-global-search
Version: 0.3.5
Summary: InvenioRDM module for the Dublin Core data model
Home-page: https://github.com/tu-graz-library/invenio-records-global-search
Author: TU Graz
Author-email: 
License: MIT
Keywords: invenio rdm data model
Platform: any
Classifier: Programming Language :: Python :: 3.12
Classifier: Development Status :: 5 - Production/Stable
Classifier: License :: OSI Approved :: MIT License
Classifier: Operating System :: OS Independent
Classifier: Programming Language :: Python
Classifier: Topic :: Software Development :: Libraries :: Python Modules
Requires-Python: >=3.12
License-File: LICENSE
License-File: AUTHORS.rst
Requires-Dist: invenio-records-resources>=4.11.3
Requires-Dist: invenio-rdm-records>=19.0.0
Requires-Dist: invenio-search-ui>=2.8.0
Requires-Dist: invenio-indexer>=2.3.0
Provides-Extra: tests
Requires-Dist: invenio-app>=2.0.0; extra == "tests"
Requires-Dist: invenio-search[opensearch2]<4.0.0,>=3.0.0; extra == "tests"
Requires-Dist: pytest-black-ng>=0.4.0; extra == "tests"
Requires-Dist: pytest-invenio<3.0.0,>=2.1.0; extra == "tests"
Requires-Dist: ruff>=0.0.263; extra == "tests"
Requires-Dist: sphinx>=4.5.0; extra == "tests"
Dynamic: license-file
